glo.py
glo_cli-0.1.0.dist-info/licenses/LICENSE
glo_cli-0.1.0.dist-info/METADATA
glo_cli-0.1.0.dist-info/WHEEL
glo_cli-0.1.0.dist-info/entry_points.txt
glo_cli-0.1.0.dist-info/top_level.txt
glo_cli-0.1.0.dist-info/RECORD
