Metadata-Version: 2.4
Name: glo-cli
Version: 0.1.0
Summary: Glogos Protocol CLI - Modern digital signatures, simpler than PGP
Author: Le Manh Thanh
License: Apache-2.0
Project-URL: Homepage, https://github.com/glogos-org/glogos
Project-URL: Documentation, https://github.com/glogos-org/glogos/blob/main/GLOGOS.md
Project-URL: Repository, https://github.com/glogos-org/glo-cli
Project-URL: Issues, https://github.com/glogos-org/glo-cli/issues
Keywords: glogos,attestation,ed25519,signing,cryptography,decentralized
Classifier: Development Status :: 4 - Beta
Classifier: Environment :: Console
Classifier: Intended Audience :: Developers
Classifier: License :: OSI Approved :: Apache Software License
Classifier: Operating System :: OS Independent
Classifier: Programming Language :: Python :: 3
Classifier: Programming Language :: Python :: 3.9
Classifier: Programming Language :: Python :: 3.10
Classifier: Programming Language :: Python :: 3.11
Classifier: Programming Language :: Python :: 3.12
Classifier: Programming Language :: Python :: 3.13
Classifier: Programming Language :: Python :: 3.14
Classifier: Topic :: Security :: Cryptography
Requires-Python: >=3.9
License-File: LICENSE
Requires-Dist: pynacl>=1.5.0
Requires-Dist: argon2-cffi>=21.0.0
Requires-Dist: cryptography>=41.0.0
Requires-Dist: mnemonic>=0.20
Dynamic: license-file
